<anotation><folder>frames</folder><filename>fileName</filename><path>path</path><source><database>Unknown</database></source><size><width>720</width><height>680</height><depth>0</depth></size><segmented>0</segmented><object><name>empty</name><pose>Unspecified</pose><truncated>0</truncated><difficult>0</difficult><bndbox><xmin>349</xmin><ymin>162</ymin><xmax>315</xmax><ymax>125</ymax></bndbox></object><object><name>empty</name><pose>Unspecified</pose><truncated>0</truncated><difficult>0</difficult><bndbox><xmin>368</xmin><ymin>319</ymin><xmax>395</xmax><ymax>160</ymax></bndbox></object></anotation>